{
  "letter": "c",
  "strokes": [
    [
      {
        "x": 0.141,
        "y": 0.768
      },
      {
        "x": 0.217,
        "y": 0.745
      },
      {
        "x": 0.285,
        "y": 0.703
      },
      {
        "x": 0.338,
        "y": 0.643
      },
      {
        "x": 0.366,
        "y": 0.569
      },
      {
        "x": 0.386,
        "y": 0.491
      },
      {
        "x": 0.406,
        "y": 0.414
      },
      {
        "x": 0.444,
        "y": 0.344
      },
      {
        "x": 0.501,
        "y": 0.289
      },
      {
        "x": 0.575,
        "y": 0.259
      },
      {
        "x": 0.654,
        "y": 0.25
      },
      {
        "x": 0.732,
        "y": 0.266
      },
      {
        "x": 0.786,
        "y": 0.324
      },
      {
        "x": 0.8,
        "y": 0.321
      },
      {
        "x": 0.745,
        "y": 0.264
      },
      {
        "x": 0.671,
        "y": 0.234
      },
      {
        "x": 0.592,
        "y": 0.234
      },
      {
        "x": 0.517,
        "y": 0.262
      },
      {
        "x": 0.455,
        "y": 0.311
      },
      {
        "x": 0.414,
        "y": 0.379
      },
      {
        "x": 0.397,
        "y": 0.457
      },
      {
        "x": 0.403,
        "y": 0.537
      },
      {
        "x": 0.428,
        "y": 0.612
      },
      {
        "x": 0.481,
        "y": 0.671
      },
      {
        "x": 0.552,
        "y": 0.708
      },
      {
        "x": 0.629,
        "y": 0.729
      },
      {
        "x": 0.708,
        "y": 0.743
      },
      {
        "x": 0.787,
        "y": 0.752
      },
      {
        "x": 0.853,
        "y": 0.754
      }
    ]
  ]
}
